README.md
setup.cfg
setup.py
sequential_uuids/__init__.py
sequential_uuids/generators.py
sequential_uuids.egg-info/PKG-INFO
sequential_uuids.egg-info/SOURCES.txt
sequential_uuids.egg-info/dependency_links.txt
sequential_uuids.egg-info/top_level.txt